tomita/__init__.py
tomita/cli.py
tomita/tomita.py
tomita/core/__init__.py
tomita/legacy/__init__.py
tomita/legacy/demosongs.py
tomita/legacy/menv.py
tomita/legacy/mixfiles.py
tomita/legacy/mkfreq.py
tomita/legacy/nokiacomposer2wav.py
tomita/legacy/play_wav.py
tomita/legacy/pysynth.py
tomita/legacy/pysynth_b.py
tomita/legacy/pysynth_beeper.py
tomita/legacy/pysynth_c.py
tomita/legacy/pysynth_d.py
tomita/legacy/pysynth_e.py
tomita/legacy/pysynth_p.py
tomita/legacy/pysynth_s.py
tomita/legacy/pysynth_samp.py
tomita/legacy/read_abc.py
tomita/legacy/readmidi.py
tomita/legacy/setup.py
tomita/legacy/test_nokiacomposer2wav.py
tomita-0.2.0.dist-info/AUTHORS.rst
tomita-0.2.0.dist-info/LICENSE
tomita-0.2.0.dist-info/METADATA
tomita-0.2.0.dist-info/WHEEL
tomita-0.2.0.dist-info/entry_points.txt
tomita-0.2.0.dist-info/top_level.txt
tomita-0.2.0.dist-info/RECORD
