Metadata-Version: 2.1
Name: tomita
Version: 0.2.0
Summary: tomita is a music and synthesizer package
Home-page: https://github.com/g4brielvs/python-tomita
Author: g4brielvs
Author-email: tomita@g4brielvs.me
License: GNU General Public License v3
Keywords: tomita
Platform: UNKNOWN
Classifier: Development Status :: 2 - Pre-Alpha
Classifier: Intended Audience :: Developers
Classifier: License :: OSI Approved :: GNU General Public License v3 (GPLv3)
Classifier: Natural Language :: English
Classifier: Programming Language :: Python :: 3
Classifier: Programming Language :: Python :: 3.5
Classifier: Programming Language :: Python :: 3.6
Classifier: Programming Language :: Python :: 3.7
Classifier: Programming Language :: Python :: 3.8
Requires-Python: >=3.5
Requires-Dist: Click (>=7.0)
Requires-Dist: numpy
